[
  {
    "cap": 20129
  },
  {
    "cap": 20131
  },
  {
    "cap": 20124
  },
  {
    "cap": 20158
  },
  {
    "cap": 20125
  },
  {
    "cap": 20142
  },
  {
    "cap": 20148
  },
  {
    "cap": 20145
  },
  {
    "cap": 20152
  },
  {
    "cap": 20137
  },
  {
    "cap": 20155
  },
  {
    "cap": 20151
  },
  {
    "cap": 20156
  },
  {
    "cap": 20161
  },
  {
    "cap": 20162
  },
  {
    "cap": 20139
  },
  {
    "cap": 20143
  },
  {
    "cap": 20135
  },
  {
    "cap": 20133
  },
  {
    "cap": 20128
  },
  {
    "cap": 20123
  },
  {
    "cap": 20141
  },
  {
    "cap": 20121
  },
  {
    "cap": 20127
  },
  {
    "cap": 20154
  },
  {
    "cap": 20153
  },
  {
    "cap": 20159
  },
  {
    "cap": 20149
  },
  {
    "cap": 20147
  },
  {
    "cap": 20122
  },
  {
    "cap": 20146
  },
  {
    "cap": 20157
  },
  {
    "cap": 20144
  },
  {
    "cap": 20134
  },
  {
    "cap": 20132
  },
  {
    "cap": 20126
  },
  {
    "cap": 20138
  },
  {
    "cap": 20136
  }
]